LICENSE
MANIFEST.in
README.md
setup.cfg
setup.py
ege_utils/__init__.py
ege_utils/apps.py
ege_utils/authentication.py
ege_utils/backends.py
ege_utils/context_processors.py
ege_utils/http.py
ege_utils/models.py
ege_utils/template_settings.py
ege_utils/urls.py
ege_utils/views.py
ege_utils/wsgi.py
ege_utils.egg-info/PKG-INFO
ege_utils.egg-info/SOURCES.txt
ege_utils.egg-info/dependency_links.txt
ege_utils.egg-info/requires.txt
ege_utils.egg-info/top_level.txt
ege_utils/templates/ege_utils/user_dont_exists.html