Metadata-Version: 1.1
Name: ege-utils
Version: 1.4.3
Summary: Utils classes for EGE project
Home-page: https://github.com/CoticEaDIFRN/ege_utils
Author: Kelson da Costa Medeiros
Author-email: kelsoncm@gmail.com
License: MIT
Download-URL: https://github.com/CoticEaDIFRN/ege_utils/releases/tag/1.4.3
Keywords: EGE,JWT,Django,Auth,SSO,client
Platform: UNKNOWN
